the_cves_cli/__init__.py
the_cves_cli/main.py
the_cves_cli/settings.py
the_cves_cli/backend_client/__init__.py
the_cves_cli/backend_client/client.py
the_cves_cli/backend_client/gen/__init__.py
the_cves_cli/backend_client/gen/models.py
the_cves_cli-0.1.10.dist-info/METADATA
the_cves_cli-0.1.10.dist-info/WHEEL
the_cves_cli-0.1.10.dist-info/entry_points.txt
the_cves_cli-0.1.10.dist-info/top_level.txt
the_cves_cli-0.1.10.dist-info/RECORD
