Metadata-Version: 2.1
Name: the-cves-cli
Version: 0.1.10
Summary: The CVEs CLI
Requires-Python: >=3.12
Requires-Dist: pydantic-settings >=2.5.2
Requires-Dist: requests >=2.32.3
Requires-Dist: typer >=0.12.5
